<odoo>
    <data>
        <record id="view_partner_form_inherit" model="ir.ui.view">
            <field name="name">res.partner.name</field>
            <field name="model">res.partner</field>
            <field name="inherit_id" ref="base.view_partner_form"/>
            <field name="arch" type="xml">
                <field name="vat" position="after">
                    <field name="is_instructor"/>
                    <field name="first_name"/>
                    <field name="middle_name"/>
                    <field name="last_name"/>
                    <field name="full_name"/>
                    <field name="age"/>
                </field>
                <!--<xpath expr='//field[@name="vat"]' position='after'>
                    <field name="is_instructor"/>
                </xpath>-->
            </field>
        </record>
    </data>
</odoo>